jutsu/__init__.py
jutsu/config.py
jutsu/downloader.py
jutsu/errors.py
jutlib-0.1.0.dist-info/LICENSE
jutlib-0.1.0.dist-info/METADATA
jutlib-0.1.0.dist-info/WHEEL
jutlib-0.1.0.dist-info/top_level.txt
jutlib-0.1.0.dist-info/RECORD
