Metadata-Version: 2.1
Name: jutlib
Version: 0.1.0
Summary: A small Python parser for installing anime episodes on user device from service jut.su
Home-page: https://github.com/BimbaXdeV/jutlib/
Download-URL: https://github.com/BimbaXdeV/jutlib/archive/refs/heads/master.zip
Author: BimbaXdeV
Author-email: kirillkirill497@gmail.com
License: MIT License
Keywords: jutsu,downloader,anime,jut
Classifier: Programming Language :: Python :: 3
Classifier: Intended Audience :: Developers
Classifier: Natural Language :: English
Classifier: Operating System :: OS Independent
Requires-Python: >=3.9
License-File: LICENSE
Requires-Dist: beautifulsoup4 (>=4.12.3)
Requires-Dist: bs4 (>=0.0.2)
Requires-Dist: certifi (>=2024.8.30)
Requires-Dist: charset-normalizer (>=3.4.0)
Requires-Dist: colorama (>=0.4.6)
Requires-Dist: idna (>=3.10)
Requires-Dist: lxml (>=5.3.0)
Requires-Dist: requests (>=2.32.3)
Requires-Dist: soupsieve (>=2.6)
Requires-Dist: tqdm (>=4.66.5)
Requires-Dist: urllib3 (>=2.2.3)
